fstab_reconfigure/__init__.py
fstab_reconfigure/__main__.py
fstab_reconfigure/programa/__init__.py
fstab_reconfigure/programa/fstab.py
fstab_reconfigure/programa/menu.py
fstab_reconfigure/programa/particiones.py
fstab_reconfigure/utiles/__init__.py
fstab_reconfigure/utiles/utiles.py
fstab_reconfigure-1.0.0.post1.dist-info/DESCRIPTION.rst
fstab_reconfigure-1.0.0.post1.dist-info/METADATA
fstab_reconfigure-1.0.0.post1.dist-info/RECORD
fstab_reconfigure-1.0.0.post1.dist-info/WHEEL
fstab_reconfigure-1.0.0.post1.dist-info/entry_points.txt
fstab_reconfigure-1.0.0.post1.dist-info/metadata.json
fstab_reconfigure-1.0.0.post1.dist-info/top_level.txt
fstab_reconfigure-1.0.0.post1.dist-info/zip-safe
